marketquant/__init__.py
marketquant/data_provider/__init__.py
marketquant/data_provider/schwab/__init__.py
marketquant/data_provider/schwab/schwab_api.py
marketquant/data_provider/schwab/schwab_init.py
marketquant/data_provider/schwab/schwab_stream.py
marketquant/math/__init__.py
marketquant/math/calculators/__init__.py
marketquant/math/calculators/interpolate.py
marketquant/math/greeks/__init__.py
marketquant/math/greeks/yfinance_greeks.py
marketquant/strategy_simulator/__init__.py
marketquant/strategy_simulator/core/__init__.py
marketquant/strategy_simulator/core/account_manager.py
marketquant/strategy_simulator/core/charting.py
marketquant/strategy_simulator/core/config.py
marketquant/strategy_simulator/core/data.py
marketquant/strategy_simulator/core/parser.py
marketquant/strategy_simulator/core/trade_engine.py
marketquant/strategy_simulator/core/trade_simulator.py
marketquant/strategy_simulator/core/cli/__init__.py
marketquant/strategy_simulator/core/cli/cli_output.py
marketquant/strategy_simulator/core/data_sources/__init__.py
marketquant/strategy_simulator/core/data_sources/schwab.py
marketquant/strategy_simulator/core/data_sources/yahoo.py
marketquant/strategy_simulator/demo_examples/__init__.py
marketquant/strategy_simulator/demo_examples/demo.py
marketquant/strategy_simulator/demo_examples/indicators/__init__.py
marketquant/strategy_simulator/demo_examples/indicators/macd.py
marketquant/strategy_simulator/demo_examples/strategies/__init__.py
marketquant/strategy_simulator/demo_examples/strategies/macd_strategy.py
marketquant/tools/__init__.py
marketquant/tools/cointegration/__init__.py
marketquant/tools/cointegration/hurst_half_life_pairs.py
marketquant/tools/cointegration/mean_analyzer.py
marketquant/tools/derivatives/__init__.py
marketquant/tools/derivatives/gamma_exposure.py
marketquant/tools/fractality/__init__.py
marketquant/tools/fractality/hldensity.py
marketquant/tools/fractality/ohlc_percentile.py
marketquant/tools/utils/__init__.py
marketquant-0.4.7.dist-info/LICENSE
marketquant-0.4.7.dist-info/METADATA
marketquant-0.4.7.dist-info/WHEEL
marketquant-0.4.7.dist-info/top_level.txt
marketquant-0.4.7.dist-info/RECORD
