Metadata-Version: 2.1
Name: marketquant
Version: 0.4.7
Summary: A quantitative market analysis tool builder library
Home-page: https://github.com/maxheltzel/MarketQuant
Author: Max Heltzel
Author-email: maxheltzel6@gmail.com
License: MPL-2.0
Project-URL: Documentation, https://market-quant.gitbook.io/home/
Project-URL: Source Code, https://github.com/maxheltzel/MarketQuant
Project-URL: Issue Tracker, https://github.com/maxheltzel/MarketQuant/issues
Project-URL: Personal Website, https://maxheltzel.net
Classifier: Programming Language :: Python :: 3
Classifier: License :: OSI Approved :: Mozilla Public License 2.0 (MPL 2.0)
Classifier: Operating System :: OS Independent
Classifier: Topic :: Software Development :: Libraries :: Python Modules
Classifier: Topic :: Scientific/Engineering :: Information Analysis
Classifier: Intended Audience :: Developers
Classifier: Intended Audience :: Financial and Insurance Industry
Requires-Python: >=3.6
License-File: LICENSE
Requires-Dist: pandas
Requires-Dist: matplotlib
Requires-Dist: mplfinance
Requires-Dist: mplcursors
Requires-Dist: yfinance
Requires-Dist: numpy
Requires-Dist: websockets
Requires-Dist: requests
Requires-Dist: python-dotenv
Requires-Dist: scipy
Requires-Dist: plotly
Requires-Dist: hurst
Requires-Dist: joblib
Requires-Dist: json
Requires-Dist: statsmodels
